ostdetector/__init__.py
ostdetector/__main__.py
ostdetector/assign_visitor.py
ostdetector/collect_visitor.py
ostdetector/get_repo.py
ostdetector/main.py
ostdetector/report.py
ostdetector/writer_csv.py
ostdetector-1.0.6.dist-info/licenses/LICENSE.txt
ostdetector-1.0.6.dist-info/METADATA
ostdetector-1.0.6.dist-info/WHEEL
ostdetector-1.0.6.dist-info/entry_points.txt
ostdetector-1.0.6.dist-info/top_level.txt
ostdetector-1.0.6.dist-info/zip-safe
ostdetector-1.0.6.dist-info/RECORD
