Metadata-Version: 2.4
Name: ostdetector
Version: 1.0.6
Summary: A tool for extracting of OS-Specific Tests
Home-page: https://github.com/ricardojob/OSTDetector
Author: Ricardo Job
License: MIT
Keywords: os-specific test detect tool
Classifier: License :: OSI Approved :: MIT License
Classifier: Topic :: Education :: Testing
Classifier: Topic :: Software Development :: Libraries :: Python Modules
Classifier: Development Status :: 5 - Production/Stable
Classifier: Intended Audience :: Education
Classifier: Intended Audience :: Developers
Classifier: Intended Audience :: Information Technology
Classifier: Intended Audience :: Science/Research
Classifier: Programming Language :: Python :: 3 :: Only
Classifier: Programming Language :: Python :: 3.8
Classifier: Programming Language :: Python :: 3.9
Classifier: Programming Language :: Python :: 3.10
Classifier: Programming Language :: Python :: 3.11
Requires-Python: ~= 3.8
License-File: LICENSE.txt
Requires-Dist: click~=8.1.7
Requires-Dist: jsonschema~=4.21.0
Dynamic: author
Dynamic: classifier
Dynamic: description
Dynamic: description-content-type
Dynamic: home-page
Dynamic: keywords
Dynamic: license
Dynamic: license-file
Dynamic: requires-dist
Dynamic: requires-python
Dynamic: summary
